{"visibleAreaProperties":[{"position":{"x":260,"y":150},"dimension":{"x":10,"y":140}},{"position":{"x":270,"y":150},"dimension":{"x":10,"y":80}},{"position":{"x":280,"y":150},"dimension":{"x":270,"y":20}},{"position":{"x":290,"y":170},"dimension":{"x":20,"y":30}},{"position":{"x":310,"y":170},"dimension":{"x":240,"y":10}},{"position":{"x":320,"y":180},"dimension":{"x":20,"y":110}},{"position":{"x":340,"y":180},"dimension":{"x":10,"y":20}},{"position":{"x":350,"y":180},"dimension":{"x":200,"y":10}},{"position":{"x":390,"y":190},"dimension":{"x":30,"y":10}},{"position":{"x":430,"y":190},"dimension":{"x":30,"y":20}},{"position":{"x":460,"y":190},"dimension":{"x":90,"y":10}},{"position":{"x":360,"y":200},"dimension":{"x":20,"y":20}},{"position":{"x":400,"y":200},"dimension":{"x":10,"y":90}},{"position":{"x":410,"y":200},"dimension":{"x":10,"y":60}},{"position":{"x":470,"y":200},"dimension":{"x":80,"y":90}},{"position":{"x":290,"y":210},"dimension":{"x":10,"y":80}},{"position":{"x":300,"y":210},"dimension":{"x":10,"y":30}},{"position":{"x":350,"y":210},"dimension":{"x":30,"y":10}},{"position":{"x":390,"y":210},"dimension":{"x":20,"y":80}},{"position":{"x":440,"y":210},"dimension":{"x":20,"y":10}},{"position":{"x":380,"y":220},"dimension":{"x":50,"y":20}},{"position":{"x":450,"y":220},"dimension":{"x":10,"y":10}},{"position":{"x":350,"y":230},"dimension":{"x":90,"y":10}},{"position":{"x":280,"y":240},"dimension":{"x":20,"y":50}},{"position":{"x":370,"y":240},"dimension":{"x":10,"y":10}},{"position":{"x":420,"y":240},"dimension":{"x":30,"y":20}},{"position":{"x":450,"y":240},"dimension":{"x":10,"y":10}},{"position":{"x":270,"y":250},"dimension":{"x":30,"y":40}},{"position":{"x":310,"y":250},"dimension":{"x":50,"y":40}},{"position":{"x":300,"y":260},"dimension":{"x":110,"y":30}},{"position":{"x":430,"y":260},"dimension":{"x":10,"y":10}},{"position":{"x":460,"y":260},"dimension":{"x":90,"y":30}},{"position":{"x":410,"y":270},"dimension":{"x":10,"y":20}},{"position":{"x":450,"y":270},"dimension":{"x":100,"y":20}},{"position":{"x":420,"y":280},"dimension":{"x":130,"y":10}},{"position":{"x":70,"y":390},"dimension":{"x":50,"y":40}}],"friendlyBarriersProperties":[{"dimension":{"x":10,"y":480}},{"position":{"x":10},"dimension":{"x":790,"y":10}},{"position":{"x":170,"y":10},"dimension":{"x":10,"y":10}},{"position":{"x":650,"y":10},"dimension":{"x":10,"y":10}},{"position":{"x":790,"y":10},"dimension":{"x":10,"y":280}},{"position":{"x":10,"y":80},"dimension":{"x":10,"y":10}},{"position":{"x":10,"y":130},"dimension":{"x":10,"y":10}},{"position":{"x":250,"y":140},"dimension":{"x":10,"y":160}},{"position":{"x":260,"y":140},"dimension":{"x":300,"y":10}},{"position":{"x":550,"y":150},"dimension":{"x":10,"y":150}},{"position":{"x":260,"y":290},"dimension":{"x":300,"y":10}},{"position":{"x":790,"y":400},"dimension":{"x":10,"y":80}},{"position":{"x":170,"y":460},"dimension":{"x":10,"y":20}},{"position":{"x":650,"y":460},"dimension":{"x":10,"y":20}},{"position":{"x":740,"y":460},"dimension":{"x":10,"y":20}},{"position":{"x":10,"y":470},"dimension":{"x":790,"y":10}}],"deadlyBarriersProperties":[{"position":{"x":280,"y":170},"dimension":{"x":10,"y":70}},{"position":{"x":310,"y":180},"dimension":{"x":10,"y":70}},{"position":{"x":350,"y":190},"dimension":{"x":10,"y":20}},{"position":{"x":360,"y":190},"dimension":{"x":30,"y":10}},{"position":{"x":420,"y":190},"dimension":{"x":10,"y":30}},{"position":{"x":290,"y":200},"dimension":{"x":30,"y":10}},{"position":{"x":340,"y":200},"dimension":{"x":10,"y":50}},{"position":{"x":380,"y":200},"dimension":{"x":10,"y":20}},{"position":{"x":390,"y":200},"dimension":{"x":10,"y":10}},{"position":{"x":460,"y":200},"dimension":{"x":10,"y":60}},{"position":{"x":430,"y":210},"dimension":{"x":10,"y":20}},{"position":{"x":350,"y":220},"dimension":{"x":30,"y":10}},{"position":{"x":440,"y":220},"dimension":{"x":10,"y":20}},{"position":{"x":270,"y":230},"dimension":{"x":10,"y":20}},{"position":{"x":450,"y":230},"dimension":{"x":20,"y":10}},{"position":{"x":300,"y":240},"dimension":{"x":10,"y":20}},{"position":{"x":350,"y":240},"dimension":{"x":20,"y":10}},{"position":{"x":380,"y":240},"dimension":{"x":10,"y":20}},{"position":{"x":360,"y":250},"dimension":{"x":30,"y":10}},{"position":{"x":450,"y":250},"dimension":{"x":10,"y":20}},{"position":{"x":410,"y":260},"dimension":{"x":20,"y":10}},{"position":{"x":440,"y":260},"dimension":{"x":10,"y":20}},{"position":{"x":420,"y":270},"dimension":{"x":30,"y":10}},{"position":{"x":780,"y":290},"dimension":{"x":20,"y":10}},{"position":{"x":790,"y":300},"dimension":{"x":10,"y":100}},{"position":{"x":60,"y":380},"dimension":{"x":10,"y":50}},{"position":{"x":70,"y":380},"dimension":{"x":50,"y":10}},{"position":{"x":700,"y":390},"dimension":{"x":10,"y":50}},{"position":{"x":710,"y":390},"dimension":{"x":90,"y":10}}],"starsProperties":[{"position":{"x":370,"y":110},"dimension":{"x":25,"y":25}},{"position":{"x":760,"y":260},"dimension":{"x":25,"y":25}}],"playerProperty":{"position":{"x":70,"y":400},"dimension":{"x":21,"y":21}},"finishPointAreaProperty":{"position":{"x":710,"y":400},"dimension":{"x":40,"y":40}},"levelHeight":480,"levelWidth":800,"breakRow":1,"breakCol":1}